eth_validation/__init__.py
eth_validation-0.1.0a1.dist-info/DESCRIPTION.rst
eth_validation-0.1.0a1.dist-info/METADATA
eth_validation-0.1.0a1.dist-info/RECORD
eth_validation-0.1.0a1.dist-info/WHEEL
eth_validation-0.1.0a1.dist-info/metadata.json
eth_validation-0.1.0a1.dist-info/top_level.txt
