Metadata-Version: 2.0
Name: eth-validation
Version: 0.1.0a1
Summary: eth-validation: Python tools for validating Ethereum-related objects
Home-page: https://github.com/ethereum/eth-validation
Author: Jason Carver
Author-email: ethcalibur+pip@gmail.com
License: MIT
Keywords: ethereum
Platform: UNKNOWN
Classifier: Development Status :: 3 - Alpha
Classifier: Intended Audience :: Developers
Classifier: License :: OSI Approved :: MIT License
Classifier: Natural Language :: English
Classifier: Programming Language :: Python :: 3
Classifier: Programming Language :: Python :: 3.5
Classifier: Programming Language :: Python :: 3.6
Requires-Dist: eth-utils (<1.0.0,>=0.7.4)
Provides-Extra: dev
Requires-Dist: bumpversion (<1,>=0.5.3); extra == 'dev'
Requires-Dist: pytest-xdist; extra == 'dev'
Requires-Dist: wheel; extra == 'dev'
Requires-Dist: pytest (==3.3.2); extra == 'dev'
Requires-Dist: tox (<3,>=2.9.1); extra == 'dev'
Requires-Dist: flake8 (==3.4.1); extra == 'dev'
Requires-Dist: isort (<5,>=4.2.15); extra == 'dev'
Requires-Dist: Sphinx (<2,>=1.6.5); extra == 'dev'
Requires-Dist: sphinx-rtd-theme (>=0.1.9); extra == 'dev'
Provides-Extra: doc
Requires-Dist: Sphinx (<2,>=1.6.5); extra == 'doc'
Requires-Dist: sphinx-rtd-theme (>=0.1.9); extra == 'doc'
Provides-Extra: lint
Requires-Dist: flake8 (==3.4.1); extra == 'lint'
Requires-Dist: isort (<5,>=4.2.15); extra == 'lint'
Provides-Extra: test
Requires-Dist: pytest (==3.3.2); extra == 'test'
Requires-Dist: tox (<3,>=2.9.1); extra == 'test'
